README
setup.py
tikatko.py
tikatko.egg-info/PKG-INFO
tikatko.egg-info/SOURCES.txt
tikatko.egg-info/dependency_links.txt
tikatko.egg-info/entry_points.txt
tikatko.egg-info/requires.txt
tikatko.egg-info/top_level.txt