Metadata-Version: 1.1
Name: tikatko
Version: 0.1
Summary: A lightning talk timer
Home-page: UNKNOWN
Author: Petr Viktorin
Author-email: encukou@gmail.com
License: UNKNOWN
Platform: UNKNOWN
Classifier: License :: OSI Approved :: MIT License
Classifier: Operating System :: OS Independent
Classifier: Programming Language :: Python
Classifier: Programming Language :: Python :: 2
Classifier: Programming Language :: Python :: 2.6
Classifier: Programming Language :: Python :: 2.7
